LICENSE
README.md
epsilab/__init__.py
epsilab/client.py
epsilab/exceptions.py
epsilab/models.py
examples/example.py
epsilab-0.1.3.dist-info/METADATA
epsilab-0.1.3.dist-info/WHEEL
epsilab-0.1.3.dist-info/licenses/LICENSE
epsilab-0.1.3.dist-info/RECORD
