Metadata-Version: 2.4
Name: epsilab
Version: 0.1.3
Summary: Python SDK for Epsilab live portfolio data (signals, weights, trades).
Project-URL: Homepage, https://www.epsilab.ai
Author: Epsilab
License:                                  Apache License
License-File: LICENSE
Classifier: License :: OSI Approved :: Apache Software License
Classifier: Operating System :: OS Independent
Classifier: Programming Language :: Python :: 3
Requires-Python: >=3.9
Requires-Dist: httpx>=0.27.0
Requires-Dist: python-dotenv>=1.0.1
